{
  "arxiv_id": "2601.05597",
  "canonical_url": "https://arxiv.org/abs/2601.05597v1",
  "pdf_url": "https://arxiv.org/pdf/2601.05597v1",
  "title": "Good Allocations from Bad Estimates",
  "abstract": "Conditional average treatment effect (CATE) estimation is the de facto gold standard for targeting a treatment to a heterogeneous population. The method estimates treatment effects up to an error $ε> 0$ in each of $M$ different strata of the population, targeting individuals in decreasing order of estimated treatment effect until the budget runs out. In general, this method requires $O(M/ε^2)$ samples. This is best possible if the goal is to estimate all treatment effects up to an $ε$ error. In this work, we show how to achieve the same total treatment effect as CATE with only $O(M/ε)$ samples for natural distributions of treatment effects. The key insight is that coarse estimates suffice for near-optimal treatment allocations. In addition, we show that budget flexibility can further reduce the sample complexity of allocation. Finally, we evaluate our algorithm on various real-world RCT datasets. In all cases, it finds nearly optimal treatment allocations with surprisingly few samples. Our work highlights the fundamental distinction between treatment effect estimation and treatment allocation: the latter requires far fewer samples.",
  "authors": [
    {
      "name": "Sílvia Casacuberta"
    },
    {
      "name": "Moritz Hardt"
    }
  ],
  "submitted_at": "2026-01-09",
  "updated_at": "2026-01-09",
  "primary_category": "cs.LG",
  "categories": [
    "cs.LG",
    "cs.CY"
  ],
  "metrics": {
    "cross_list_count": 1,
    "version_count": 1,
    "trending_score": 0.5597,
    "recent_score": 0.21,
    "canonical_score": 0.6755,
    "max_topic_confidence": 0.89,
    "rising_score": 0.5211
  },
  "topic_tags": [
    {
      "topic_id": "effect-estimation",
      "confidence": 0.89,
      "rationale": {
        "matched_keywords": [
          "treatment effect",
          "ate",
          "cate"
        ],
        "rules_version": "v2"
      }
    },
    {
      "topic_id": "instrumental-variables",
      "confidence": 0.73,
      "rationale": {
        "matched_keywords": [
          "IV"
        ],
        "rules_version": "v2"
      }
    }
  ],
  "versions": [
    {
      "version": "v1",
      "updated_at": "2026-01-09"
    }
  ],
  "links": {
    "arxiv_abs": "https://arxiv.org/abs/2601.05597v1",
    "arxiv_pdf": "https://arxiv.org/pdf/2601.05597v1"
  },
  "provenance": {
    "source": "arxiv_api",
    "harvested_at": "2026-03-05T23:52:40.464Z",
    "harvest_run_id": "snapshot-2026-03-05",
    "queries": [
      "((abs:CATE OR abs:ATE OR abs:uplift) AND (abs:causal OR abs:\"treatment effect\"))"
    ],
    "query_packs": [
      "discovery-inference"
    ]
  },
  "application_tags": []
}